aiobrultech_serial/__init__.py
aiobrultech_serial/exceptions.py
aiobrultech_serial/py.typed
aiobrultech_serial-0.9.0.dist-info/LICENSE
aiobrultech_serial-0.9.0.dist-info/METADATA
aiobrultech_serial-0.9.0.dist-info/WHEEL
aiobrultech_serial-0.9.0.dist-info/top_level.txt
aiobrultech_serial-0.9.0.dist-info/RECORD
