Metadata-Version: 2.1
Name: aiobrultech-serial
Version: 0.9.0
Summary: A Python client library to talk with Brultech Devices over a serial connection
Author: Shawn Wilsher
Author-email: me@shawnwilsher.com
Project-URL: Bug Reports, https://github.com/sdwilsh/aiobrultech-serial/issues
Project-URL: Release Notes, https://github.com/sdwilsh/aiobrultech-serial/releases/
Project-URL: Source, https://github.com/sdwilsh/aiobrultech-serial
Classifier: Development Status :: 4 - Beta
Classifier: License :: OSI Approved :: MIT License
Classifier: Operating System :: OS Independent
Classifier: Programming Language :: Python :: 3.8
Classifier: Programming Language :: Python :: 3.9
Classifier: Programming Language :: Python :: 3.10
Classifier: Programming Language :: Python :: 3.11
Classifier: Programming Language :: Python :: 3.12
Requires-Python: <4,>=3.8
License-File: LICENSE
Requires-Dist: pyserial >=3.5
Requires-Dist: pyserial-asyncio ==0.6
Requires-Dist: siobrultech-protocols ==0.14.0
